shshsh/__init__.py
shshsh/global_vars.py
shshsh/pipe.py
shshsh/quick.py
shshsh/shell.py
shshsh/streamer.py
shshsh/utils.py
shshsh-1.0.6.dist-info/LICENSE
shshsh-1.0.6.dist-info/METADATA
shshsh-1.0.6.dist-info/WHEEL
shshsh-1.0.6.dist-info/RECORD
