Metadata-Version: 2.1
Name: shshsh
Version: 1.0.6
Summary: bridge of python and shell
Home-page: https://github.com/zqqqqz2000/shshsh
Author: zqqqqz2000
Author-email: zqqqqz2000@sina.cn
Requires-Python: >=3.8,<4.0
Classifier: Programming Language :: Python :: 3
Classifier: Programming Language :: Python :: 3.8
Classifier: Programming Language :: Python :: 3.9
Classifier: Programming Language :: Python :: 3.10
Classifier: Programming Language :: Python :: 3.11
Classifier: Programming Language :: Python :: 3.12
Project-URL: Repository, https://github.com/zqqqqz2000/shshsh
